LICENSE.txt
README.md
awesome_object_store/__init__.py
awesome_object_store/base.py
awesome_object_store/gcs.py
awesome_object_store/minio.py
awesome_object_store-3.0.0.dist-info/LICENSE.txt
awesome_object_store-3.0.0.dist-info/METADATA
awesome_object_store-3.0.0.dist-info/WHEEL
awesome_object_store-3.0.0.dist-info/RECORD
