Metadata-Version: 2.1
Name: awesome-object-store
Version: 3.0.0
Summary: minio wrapper to perform task like pandas dataframe upload, download
Home-page: https://github.com/MoBagel/awesome-object-store
License: Apache-2.0
Author: Schwannden Kuo
Author-email: schwannden@mobagel.com
Requires-Python: >=3.9,<3.12
Classifier: Development Status :: 1 - Planning
Classifier: Intended Audience :: Developers
Classifier: Intended Audience :: Information Technology
Classifier: License :: OSI Approved :: Apache Software License
Classifier: Operating System :: OS Independent
Classifier: Programming Language :: Python :: 3
Classifier: Programming Language :: Python :: 3.9
Classifier: Programming Language :: Python :: 3.10
Classifier: Programming Language :: Python :: 3.11
Classifier: Programming Language :: Python :: 3.8
Classifier: Programming Language :: Python :: Implementation :: PyPy
Classifier: Topic :: Internet
Classifier: Topic :: Internet :: WWW/HTTP
Classifier: Topic :: Software Development :: Libraries
Classifier: Topic :: Software Development :: Libraries :: Application Frameworks
Classifier: Topic :: Software Development :: Libraries :: Python Modules
Requires-Dist: google-cloud-storage (==1.44.0)
Requires-Dist: minio (>=7.1.1,<8.0.0)
Requires-Dist: pandas (>=2.0.0,<3.0.0)
Requires-Dist: starlette (>=0.16.0)
